DeepSecE/__init__.py
DeepSecE/dataset.py
DeepSecE/model.py
DeepSecE/module.py
DeepSecE/trainer.py
DeepSecE/utils.py
DeepSecE-0.1.0.dist-info/LICENSE
DeepSecE-0.1.0.dist-info/METADATA
DeepSecE-0.1.0.dist-info/WHEEL
DeepSecE-0.1.0.dist-info/top_level.txt
DeepSecE-0.1.0.dist-info/RECORD
