Metadata-Version: 2.1
Name: DeepSecE
Version: 0.1.0
Summary: A Deep Learning Framework for Multi-class Secreted Effector Prediction in Gram-negative Bacteria.
Home-page: https://github.com/zhangyumeng1sjtu/DeepSecE
Author: Yumeng Zhang
License: MIT
Platform: UNKNOWN
License-File: LICENSE
Requires-Dist: torch
Requires-Dist: biopython
Requires-Dist: einops
Requires-Dist: fair-esm
Requires-Dist: tqdm
Requires-Dist: numpy
Requires-Dist: scikit-learn
Requires-Dist: matplotlib
Requires-Dist: seaborn
Requires-Dist: tensorboardX
Requires-Dist: umap-learn
Requires-Dist: warmup-scheduler
